queensgym/__init__.py
queensgym-0.0.1.dist-info/METADATA
queensgym-0.0.1.dist-info/WHEEL
queensgym-0.0.1.dist-info/top_level.txt
queensgym-0.0.1.dist-info/RECORD
