Metadata-Version: 2.4
Name: queensgym
Version: 0.0.1
Summary: A simple API to train RL models in n-queens and other related problems.
License: MIT License
Project-URL: repository, https://github.com/aciriano/QueensGym
Keywords: Reinforcement Learning,RL,n-Queens,queens
Classifier: License :: OSI Approved :: MIT License
Classifier: Programming Language :: Python :: 3
Classifier: Programming Language :: Python :: 3.10
Requires-Python: >=3.10
Requires-Dist: numpy==2.2.6
Requires-Dist: pygame==2.6.1
Provides-Extra: dev
Requires-Dist: ruff; extra == "dev"
Requires-Dist: pytest; extra == "dev"
Requires-Dist: pre-commit; extra == "dev"
Requires-Dist: pytest-cov; extra == "dev"
Requires-Dist: tox; extra == "dev"
Requires-Dist: reorder-python-imports; extra == "dev"
Requires-Dist: mypy; extra == "dev"
